dataproc_ml-1.0.0rc1.dist-info/licenses/LICENSE
google/cloud/dataproc_ml/__init__.py
google/cloud/dataproc_ml/_utils/__init__.py
google/cloud/dataproc_ml/_utils/_gcs_utils.py
google/cloud/dataproc_ml/inference/__init__.py
google/cloud/dataproc_ml/inference/base_model_handler.py
google/cloud/dataproc_ml/inference/gen_ai_model_handler.py
google/cloud/dataproc_ml/inference/pytorch_model_handler.py
google/cloud/dataproc_ml/inference/tensorflow_model_handler.py
google/cloud/dataproc_ml/inference/vertex_endpoint_handler.py
dataproc_ml-1.0.0rc1.dist-info/METADATA
dataproc_ml-1.0.0rc1.dist-info/WHEEL
dataproc_ml-1.0.0rc1.dist-info/top_level.txt
dataproc_ml-1.0.0rc1.dist-info/RECORD
