Metadata-Version: 2.4
Name: dataproc-ml
Version: 1.0.0rc1
Summary: A python library to ease MLOps for Dataproc customers
Author: Google LLC
License-Expression: Apache-2.0
Project-URL: Homepage, https://github.com/GoogleCloudDataproc/dataproc-ml-python
Project-URL: Documentation, https://dataproc-ml.readthedocs.io/
Project-URL: Issues, https://github.com/GoogleCloudDataproc/dataproc-ml-python/issues
Classifier: Intended Audience :: Developers
Classifier: Operating System :: OS Independent
Classifier: Programming Language :: Python :: 3
Classifier: Programming Language :: Python :: 3.12
Classifier: Topic :: Software Development :: Libraries :: Python Modules
Requires-Python: >=3.12
License-File: LICENSE
Requires-Dist: google-cloud-aiplatform<2.0.0,>=1.121.0
Requires-Dist: google-cloud-storage<3.0.0,>=2.19.0
Requires-Dist: pandas<3.0.0,>=2.2.2
Requires-Dist: pyarrow<20.0.0,>=18.1.0
Requires-Dist: tenacity<9.0.0,>=8.5.0
Requires-Dist: tensorflow<2.20.0,>=2.18.0
Requires-Dist: torch<3.0.0,>=2.6.0
Provides-Extra: test
Requires-Dist: pytest; extra == "test"
Requires-Dist: torchvision<1.0.0,>=0.21.0; extra == "test"
Requires-Dist: pillow<12.0.0,>=11.3.0; extra == "test"
Requires-Dist: pyspark~=4.0.0; extra == "test"
Provides-Extra: dev
Requires-Dist: pyink; extra == "dev"
Requires-Dist: pylint; extra == "dev"
Requires-Dist: build; extra == "dev"
Provides-Extra: docs
Requires-Dist: sphinx; extra == "docs"
Requires-Dist: sphinx_rtd_theme; extra == "docs"
Dynamic: license-file
